{
    "$schema": "http://schema.management.azure.com/schemas/2014-04-01-preview/deploymentParameters.json#",
    "contentVersion": "1.0.0.0",
    "parameters": {
        "newStorageAccountName": {
                "value": "garstoragetest1789"
        },
        "adminUsername": {
                "value": "test-user"
        },
        "adminPassword": {
                "value": "Abcd1234@"
        },
        "dnsNameForPublicIP": {
                "value": "testdomain1789"
        },
        "ubuntuOSVersion": {
                "value": ""
        },
        "slaveCount": {
                "value":  1
        },
        "swarmClusterId": {
                "value": "0a035dff9ea329bd554092cd902ba9f7"
        }
   }
}
